{
"type": "FeatureCollection",
"name": "patch_sumba_v0.0.7_2019-01-01_2021-06-01mosaic-median_blobs_thresh_0.8_min-sigma_5_area-thresh_0.0025",
"crs": { "type": "name", "properties": { "name": "urn:ogc:def:crs:OGC:1.3:CRS84" } },
"features": [
{ "type": "Feature", "properties": { "name": "sumba_v0.0.7_2019-01-01_2021-06-01mosaic-median_1", "mean": 0.17709699273109436, "std": 0.24342699348926544, "min": 0.0033839999232441187, "max": 0.59449702501296997, "count": 4 }, "geometry": { "type": "Point", "coordinates": [ 120.405031021690803, -9.640927819815603 ] } },
{ "type": "Feature", "properties": { "name": "sumba_v0.0.7_2019-01-01_2021-06-01mosaic-median_2", "mean": 0.01448300015181303, "std": 0.021776000037789345, "min": 0.0, "max": 0.052103001624345779, "count": 4 }, "geometry": { "type": "Point", "coordinates": [ 120.36676100034208, -9.652343192285661 ] } },
{ "type": "Feature", "properties": { "name": "sumba_v0.0.7_2019-01-01_2021-06-01mosaic-median_3", "mean": 0.040856000036001205, "std": 0.044723998755216599, "min": 0.00013600000238511711, "max": 0.11130700260400772, "count": 4 }, "geometry": { "type": "Point", "coordinates": [ 120.459272139277871, -9.620972893613001 ] } },
{ "type": "Feature", "properties": { "name": "sumba_v0.0.7_2019-01-01_2021-06-01mosaic-median_4", "mean": 0.28955599665641785, "std": 0.277211993932724, "min": 0.021372999995946884, "max": 0.7456660270690918, "count": 4 }, "geometry": { "type": "Point", "coordinates": [ 119.919659420523075, -9.832017956366039 ] } },
{ "type": "Feature", "properties": { "name": "sumba_v0.0.7_2019-01-01_2021-06-01mosaic-median_5", "mean": 0.63986802101135254, "std": 0.36023500561714172, "min": 0.058325000107288361, "max": 0.999642014503479, "count": 4 }, "geometry": { "type": "Point", "coordinates": [ 120.57187729287449, -9.771379410998996 ] } },
{ "type": "Feature", "properties": { "name": "sumba_v0.0.7_2019-01-01_2021-06-01mosaic-median_6", "mean": 0.0, "std": 0.0, "min": 0.0, "max": 0.0, "count": 4 }, "geometry": { "type": "Point", "coordinates": [ 120.349936438966949, -9.654202510389114 ] } },
{ "type": "Feature", "properties": { "name": "sumba_v0.0.7_2019-01-01_2021-06-01mosaic-median_7", "mean": 0.98959600925445557, "std": 0.01127300038933754, "min": 0.97097599506378174, "max": 0.99871200323104858, "count": 4, "dump": true }, "geometry": { "type": "Point", "coordinates": [ 120.335349096856035, -9.717151051418734 ] } }
]
}
