{
"type": "FeatureCollection",
"features": [
{ "type": "Feature", "properties": { "name": "city_0" }, "geometry": { "type": "Point", "coordinates": [ 114.619837462397498, -8.361931821454325 ] } },
{ "type": "Feature", "properties": { "name": "city_1" }, "geometry": { "type": "Point", "coordinates": [ 115.218991577306397, -8.682542635447703 ] } },
{ "type": "Feature", "properties": { "name": "city_2" }, "geometry": { "type": "Point", "coordinates": [ 115.152099133756195, -8.803351890677076 ] } },
{ "type": "Feature", "properties": { "name": "city_3" }, "geometry": { "type": "Point", "coordinates": [ 115.448223410024198, -8.676354239123828 ] } },
{ "type": "Feature", "properties": { "name": "city_4" }, "geometry": { "type": "Point", "coordinates": [ 115.5521252514949, -8.674258048038155 ] } },
{ "type": "Feature", "properties": { "name": "city_5" }, "geometry": { "type": "Point", "coordinates": [ 115.401409030608505, -8.538239298420237 ] } },
{ "type": "Feature", "properties": { "name": "city_6" }, "geometry": { "type": "Point", "coordinates": [ 115.612110467227893, -8.445371131588061 ] } },
{ "type": "Feature", "properties": { "name": "city_7" }, "geometry": { "type": "Point", "coordinates": [ 115.313558020448198, -8.116868687570463 ] } },
{ "type": "Feature", "properties": { "name": "city_8" }, "geometry": { "type": "Point", "coordinates": [ 115.338570699921405, -8.125140997178228 ] } },
{ "type": "Feature", "properties": { "name": "city_9" }, "geometry": { "type": "Point", "coordinates": [ 115.084821337184707, -8.116446736800448 ] } },
{ "type": "Feature", "properties": { "name": "city_10" }, "geometry": { "type": "Point", "coordinates": [ 115.566599519184194, -8.479447188444803 ] } },
{ "type": "Feature", "properties": { "name": "city_11" }, "geometry": { "type": "Point", "coordinates": [ 115.270774366247494, -8.524372886001233 ] } },
{ "type": "Feature", "properties": { "name": "city_12" }, "geometry": { "type": "Point", "coordinates": [ 115.321225723729896, -8.543492283694 ] } },
{ "type": "Feature", "properties": { "name": "city_13" }, "geometry": { "type": "Point", "coordinates": [ 114.8212475611857, -8.419915648919948 ] } },
{ "type": "Feature", "properties": { "name": "city_14" }, "geometry": { "type": "Point", "coordinates": [ 115.176788640229105, -8.715171414596252 ] } },
{ "type": "Feature", "properties": { "name": "city_15" }, "geometry": { "type": "Point", "coordinates": [ 115.233427164838403, -8.651256172192152 ] } },
{ "type": "Feature", "properties": { "name": "city_16" }, "geometry": { "type": "Point", "coordinates": [ 115.190052014447303, -8.657268736255549 ] } },
{ "type": "Feature", "properties": { "name": "city_17" }, "geometry": { "type": "Point", "coordinates": [ 115.197154463012694, -8.625681886747383 ] } },
{ "type": "Feature", "properties": { "name": "city_18" }, "geometry": { "type": "Point", "coordinates": [ 115.261959364986694, -8.630529740980601 ] } },
{ "type": "Feature", "properties": { "name": "city_19" }, "geometry": { "type": "Point", "coordinates": [ 115.237772219426702, -8.693875555404086 ] } },
{ "type": "Feature", "properties": { "name": "city_20" }, "geometry": { "type": "Point", "coordinates": [ 115.196367719228903, -8.821411623234093 ] } },
{ "type": "Feature", "properties": { "name": "city_21" }, "geometry": { "type": "Point", "coordinates": [ 115.124251585012999, -8.831537261804662 ] } },
{ "type": "Feature", "properties": { "name": "city_22" }, "geometry": { "type": "Point", "coordinates": [ 115.356294505677894, -8.452360524836058 ] } },
{ "type": "Feature", "properties": { "name": "city_23" }, "geometry": { "type": "Point", "coordinates": [ 114.588736145522702, -8.396892858569597 ] } },
{ "type": "Feature", "properties": { "name": "city_24" }, "geometry": { "type": "Point", "coordinates": [ 114.917242476678197, -8.419241928456261 ] } },
{ "type": "Feature", "properties": { "name": "city_25" }, "geometry": { "type": "Point", "coordinates": [ 114.370932273082005, -8.212168765884828 ] } },
{ "type": "Feature", "properties": { "name": "city_26" }, "geometry": { "type": "Point", "coordinates": [ 114.383592787971295, -8.231051158486935 ] } },
{ "type": "Feature", "properties": { "name": "city_27" }, "geometry": { "type": "Point", "coordinates": [ 114.435515245793198, -8.171251579503354 ] } },
{ "type": "Feature", "properties": { "name": "city_28" }, "geometry": { "type": "Point", "coordinates": [ 115.151088313608, -8.248838505575904 ] } },
{ "type": "Feature", "properties": { "name": "city_29" }, "geometry": { "type": "Point", "coordinates": [ 114.335584596148394, -8.439057457803544 ] } },
{ "type": "Feature", "properties": { "name": "city_30" }, "geometry": { "type": "Point", "coordinates": [ 114.934153176066303, -8.193097409513378 ] } }
]
}
