{
"type": "FeatureCollection",
"crs": { "type": "name", "properties": { "name": "urn:ogc:def:crs:OGC:1.3:CRS84" } },
"features": [
{ "type": "Feature", "properties": { "lon": 126.50319781528155, "lat": -8.4595166569138129, "name": "east_timor_v0.0.11_2019-01-01_2021-06-01mosaic-median_33" }, "geometry": { "type": "Point", "coordinates": [ 126.503197815281553, -8.459516656913813 ] } },
{ "type": "Feature", "properties": { "lon": 125.61062594051826, "lat": -8.2181611384902045, "name": "east_timor_v0.0.11_2019-01-01_2021-06-01mosaic-median_58" }, "geometry": { "type": "Point", "coordinates": [ 125.610625940518261, -8.218161138490204 ] } },
{ "type": "Feature", "properties": { "lon": 125.70097960466163, "lat": -8.5341210544879669, "name": "east_timor_v0.0.11_2019-01-01_2021-06-01mosaic-median_60" }, "geometry": { "type": "Point", "coordinates": [ 125.700979604661626, -8.534121054487967 ] } },
{ "type": "Feature", "properties": { "lon": 126.5313168842585, "lat": -8.4683010359500877, "name": "east_timor_v0.0.11_2019-01-01_2021-06-01mosaic-median_99" }, "geometry": { "type": "Point", "coordinates": [ 126.531316884258501, -8.468301035950088 ] } },
{ "type": "Feature", "properties": { "lon": 125.48564774438887, "lat": -8.5690265494552307, "name": "east_timor_v0.0.11_2019-01-01_2021-06-01mosaic-median_102" }, "geometry": { "type": "Point", "coordinates": [ 125.485647744388871, -8.569026549455231 ] } }
]
}
